decent_bench/__init__.py
decent_bench/agent.py
decent_bench/benchmark.py
decent_bench/benchmark_problem.py
decent_bench/centralized_algorithms.py
decent_bench/cost_functions.py
decent_bench/datasets.py
decent_bench/distributed_algorithms.py
decent_bench/network.py
decent_bench/schemes.py
decent_bench/metrics/__init__.py
decent_bench/metrics/metric_utils.py
decent_bench/metrics/plot_metrics.py
decent_bench/metrics/table_metrics.py
decent_bench/utils/__init__.py
decent_bench/utils/logger.py
decent_bench/utils/progress_bar.py
decent_bench-0.2.2.dist-info/METADATA
decent_bench-0.2.2.dist-info/WHEEL
decent_bench-0.2.2.dist-info/licenses/LICENSE
decent_bench-0.2.2.dist-info/RECORD
