Metadata-Version: 2.4
Name: decent-bench
Version: 0.2.2
Summary: A benchmarking framework for decentralized optimization
Project-URL: Documentation, https://decent-bench.readthedocs.io/en/latest/
Project-URL: Source, https://github.com/team-decent/decent-bench
Project-URL: Issues, https://github.com/team-decent/decent-bench/issues
Author: Elias Ram, Nicola Bastianello
Maintainer: Team Decent
License-Expression: AGPL-3.0-only
License-File: LICENSE
Classifier: Operating System :: OS Independent
Classifier: Programming Language :: Python :: 3.13
Requires-Python: >=3.13
Requires-Dist: matplotlib
Requires-Dist: networkx
Requires-Dist: numpy
Requires-Dist: rich
Requires-Dist: scikit-learn
Requires-Dist: scipy
Requires-Dist: tabulate
Provides-Extra: dev
Requires-Dist: hatch; extra == 'dev'
Requires-Dist: mypy; extra == 'dev'
Requires-Dist: pytest; extra == 'dev'
Requires-Dist: ruff; extra == 'dev'
Requires-Dist: scipy-stubs; extra == 'dev'
Requires-Dist: sphinx; extra == 'dev'
Requires-Dist: types-networkx; extra == 'dev'
Requires-Dist: types-tabulate; extra == 'dev'
